glow/__init__.py
glow/activations.py
glow/dynamics.py
glow/hash_functions.py
glow/layer.py
glow/losses.py
glow/metrics.py
glow/tensor_numpy_adapter.py
glow/datasets/__init__.py
glow/datasets/cifar10.py
glow/datasets/mnist.py
glow/information_bottleneck/__init__.py
glow/information_bottleneck/estimator.py
glow/layers/__init__.py
glow/layers/convolutional.py
glow/layers/core.py
glow/layers/hsic_output.py
glow/layers/normalization.py
glow/layers/pooling.py
glow/models/__init__.py
glow/models/hsic.py
glow/models/network.py
glow/preprocessing/__init__.py
glow/preprocessing/data_generator.py
glow/utils/__init__.py
glow/utils/hash_functions.py
glow/utils/hsic_utils.py
glow/utils/optimizers.py
PyGlow-0.1.7.dist-info/LICENSE
PyGlow-0.1.7.dist-info/METADATA
PyGlow-0.1.7.dist-info/WHEEL
PyGlow-0.1.7.dist-info/entry_points.txt
PyGlow-0.1.7.dist-info/top_level.txt
PyGlow-0.1.7.dist-info/RECORD
