Metadata-Version: 2.1
Name: PyGlow
Version: 0.1.7
Summary: Information Theory of Deep Learning
Home-page: https://github.com/spino17/PyGlow
Author: Bhavya Bhatt
Author-email: bhavyabhatt17@gmail.com
License: BSD 3-clause
Platform: UNKNOWN
Classifier: License :: OSI Approved :: BSD License
Classifier: Programming Language :: Python :: 3
Classifier: Programming Language :: Python :: 3.7
Requires-Dist: torch (>=1.1.0)
Requires-Dist: numpy (>=1.15.0)
Requires-Dist: torchvision
Requires-Dist: tqdm (>=4.30.0)
